<?xml version="1.0" encoding="UTF-8"?>
<databaseChangeLog
        xmlns="http://www.liquibase.org/xml/ns/dbchangelog"
        xmlns:xsi="http://www.w3.org/2001/XMLSchema-instance"
        logicalFilePath="db/changelog/v2__seed.xml"
        xsi:schemaLocation="
        http://www.liquibase.org/xml/ns/dbchangelog
        http://www.liquibase.org/xml/ns/dbchangelog/dbchangelog-4.3.xsd">

    <changeSet id="v2-017-seed-search-logs" author="minh" xmlns="http://www.liquibase.org/xml/ns/dbchangelog"><!-- user 2 --><insert tableName="search_logs"><column name="id" valueNumeric="1" /><column name="user_id" valueNumeric="2" /><column name="keyword" value="smartphone" /></insert><insert tableName="search_logs"><column name="id" valueNumeric="2" /><column name="user_id" valueNumeric="2" /><column name="keyword" value="smartphone x20" /></insert><!-- user 3 --><insert tableName="search_logs"><column name="id" valueNumeric="3" /><column name="user_id" valueNumeric="3" /><column name="keyword" value="laptop pro 14" /></insert><insert tableName="search_logs"><column name="id" valueNumeric="4" /><column name="user_id" valueNumeric="3" /><column name="keyword" value="clean code" /></insert><!-- user 4 --><insert tableName="search_logs"><column name="id" valueNumeric="5" /><column name="user_id" valueNumeric="4" /><column name="keyword" value="women dress" /></insert><!-- guest (user_id = NULL) --><insert tableName="search_logs"><column name="id" valueNumeric="6" /><column name="keyword" value="wireless headphones" /></insert><insert tableName="search_logs"><column name="id" valueNumeric="7" /><column name="keyword" value="power bank 20000mah" /></insert><insert tableName="search_logs"><column name="id" valueNumeric="8" /><column name="keyword" value="men tshirt" /></insert><insert tableName="search_logs"><column name="id" valueNumeric="9" /><column name="user_id" valueNumeric="7" /><column name="keyword" value="tablet pro 11" /></insert><insert tableName="search_logs"><column name="id" valueNumeric="10" /><column name="user_id" valueNumeric="8" /><column name="keyword" value="mirrorless camera" /></insert><insert tableName="search_logs"><column name="id" valueNumeric="11" /><column name="user_id" valueNumeric="9" /><column name="keyword" value="magsafe case" /></insert><insert tableName="search_logs"><column name="id" valueNumeric="12" /><column name="user_id" valueNumeric="10" /><column name="keyword" value="hoodie" /></insert><insert tableName="search_logs"><column name="id" valueNumeric="13" /><column name="user_id" valueNumeric="11" /><column name="keyword" value="sneakers" /></insert><insert tableName="search_logs"><column name="id" valueNumeric="14" /><column name="user_id" valueNumeric="12" /><column name="keyword" value="action camera" /></insert><insert tableName="search_logs"><column name="id" valueNumeric="15" /><column name="keyword" value="best laptop for dev" /></insert><rollback><delete tableName="search_logs"><where>id BETWEEN 1 AND 15</where></delete></rollback></changeSet>

</databaseChangeLog>
